pymysqlpool.py
pymysql_pool-0.5.0.dist-info/LICENSE
pymysql_pool-0.5.0.dist-info/METADATA
pymysql_pool-0.5.0.dist-info/WHEEL
pymysql_pool-0.5.0.dist-info/top_level.txt
pymysql_pool-0.5.0.dist-info/RECORD
