Metadata-Version: 2.1
Name: pymysql-pool
Version: 0.5.0
Summary: MySQL connection pool based pymysql
Author-email: ljk <chaoyuemyself@hotmail.com>
License: GPL-3.0
Project-URL: Homepage, https://github.com/jkklee/pymysql-pool
Keywords: pymysql pool,mysql connection pool,mysql multi threads
Requires-Python: >=3.7
License-File: LICENSE
Requires-Dist: pymysql >=0.7.10
